snake_egg-0.1.0.dist-info/METADATA
snake_egg-0.1.0.dist-info/WHEEL
snake_egg-0.1.0.dist-info/license_files/LICENSE
snake_egg/__init__.pyi
snake_egg/tests/test_simple.py
snake_egg/tests/test_egg_interface.py
snake_egg/tests/test_prop.py
snake_egg/tests/test_dynamic.py
snake_egg/tests/test_math.py
snake_egg/tests/test_dataclass.py
snake_egg/__init__.py
snake_egg/py.typed
snake_egg/_internal.cpython-39-darwin.so
snake_egg-0.1.0.dist-info/RECORD
