Metadata-Version: 2.1
Name: snake-egg
Version: 0.1.0
Requires-Dist: mypy; extra == 'dev'
Provides-Extra: dev
License-File: LICENSE
Requires-Python: >=3.7
